NanoSim_H-1.1.0.4.dist-info/METADATA
NanoSim_H-1.1.0.4.dist-info/RECORD
NanoSim_H-1.1.0.4.dist-info/WHEEL
NanoSim_H-1.1.0.4.dist-info/entry_points.txt
NanoSim_H-1.1.0.4.dist-info/top_level.txt
nanosimh/__init__.py
nanosimh/besthit_to_histogram.py
nanosimh/get_besthit.py
nanosimh/head_align_tail_dist.py
nanosimh/increment_version.py
nanosimh/misc.py
nanosimh/mixed_models.py
nanosimh/model_fitting.R
nanosimh/simulate.py
nanosimh/train.py
nanosimh/version.py
nanosimh/profiles/ecoli_R7/align_ratio
nanosimh/profiles/ecoli_R7/aligned_length_ecdf
nanosimh/profiles/ecoli_R7/aligned_reads_ecdf
nanosimh/profiles/ecoli_R7/del.hist
nanosimh/profiles/ecoli_R7/error_markov_model
nanosimh/profiles/ecoli_R7/first_match.hist
nanosimh/profiles/ecoli_R7/ht_ratio
nanosimh/profiles/ecoli_R7/ins.hist
nanosimh/profiles/ecoli_R7/match.hist
nanosimh/profiles/ecoli_R7/match_markov_model
nanosimh/profiles/ecoli_R7/mis.hist
nanosimh/profiles/ecoli_R7/model_profile
nanosimh/profiles/ecoli_R7/unaligned_length_ecdf
nanosimh/profiles/ecoli_R7.3/align_ratio
nanosimh/profiles/ecoli_R7.3/aligned_length_ecdf
nanosimh/profiles/ecoli_R7.3/aligned_reads_ecdf
nanosimh/profiles/ecoli_R7.3/del.hist
nanosimh/profiles/ecoli_R7.3/error_markov_model
nanosimh/profiles/ecoli_R7.3/first_match.hist
nanosimh/profiles/ecoli_R7.3/ht_ratio
nanosimh/profiles/ecoli_R7.3/ins.hist
nanosimh/profiles/ecoli_R7.3/match.hist
nanosimh/profiles/ecoli_R7.3/match_markov_model
nanosimh/profiles/ecoli_R7.3/mis.hist
nanosimh/profiles/ecoli_R7.3/model_profile
nanosimh/profiles/ecoli_R7.3/unaligned_length_ecdf
nanosimh/profiles/ecoli_R9_1D/align_ratio
nanosimh/profiles/ecoli_R9_1D/aligned_length_ecdf
nanosimh/profiles/ecoli_R9_1D/aligned_reads_ecdf
nanosimh/profiles/ecoli_R9_1D/del.hist
nanosimh/profiles/ecoli_R9_1D/error_markov_model
nanosimh/profiles/ecoli_R9_1D/first_match.hist
nanosimh/profiles/ecoli_R9_1D/ht_ratio
nanosimh/profiles/ecoli_R9_1D/ins.hist
nanosimh/profiles/ecoli_R9_1D/match.hist
nanosimh/profiles/ecoli_R9_1D/match_markov_model
nanosimh/profiles/ecoli_R9_1D/mis.hist
nanosimh/profiles/ecoli_R9_1D/model_profile
