Metadata-Version: 2.1
Name: NanoSim-H
Version: 1.1.0.4
Summary: UNKNOWN
Home-page: https://github.com/karel-brinda/nanosim-h
Author: UNKNOWN
Author-email: UNKNOWN
License: GPLv3
Keywords: Nanopore simulation
Platform: UNKNOWN
Classifier: Development Status :: 4 - Beta
Classifier: Intended Audience :: Developers
Classifier: Topic :: Software Development :: Build Tools
Classifier: License :: OSI Approved :: GNU General Public License v3 (GPLv3)
Classifier: Programming Language :: Python :: 2
Classifier: Programming Language :: Python :: 2.7
Classifier: Programming Language :: Python :: 3
Classifier: Programming Language :: Python :: 3.3
Classifier: Programming Language :: Python :: 3.4
Classifier: Programming Language :: Python :: 3.5
Classifier: Programming Language :: Python :: 3.6
Requires-Dist: numpy
Requires-Dist: progressbar2
